{
  "type": "FeatureCollection",
  "features": [
    {
      "type": "Feature",
      "properties": {
        "name": "Beijing",
        "name_zh": "北京"
      },
      "geometry": {
        "type": "Point",
        "coordinates": [116.4074, 39.9042]
      }
    },
    {
      "type": "Feature",
      "properties": {
        "name": "Shanghai",
        "name_zh": "上海"
      },
      "geometry": {
        "type": "Point",
        "coordinates": [121.4737, 31.2304]
      }
    },
    {
      "type": "Feature",
      "properties": {
        "name": "Ottawa",
        "name_zh": "渥太华"
      },
      "geometry": {
        "type": "Point",
        "coordinates": [-75.6972, 45.4215]
      }
    }
  ]
}
